tinder/__init__.py
tinder/client.py
tinder/errors.py
tinder/gateway.py
tinder/http.py
tinder/models/__init__.py
tinder/models/abc.py
tinder/models/asset.py
tinder/models/user.py
tinder/state.py
tinder/types.py
tinder/utils.py
tinder.py-0.1.1.dist-info/WHEEL
tinder.py-0.1.1.dist-info/METADATA
tinder.py-0.1.1.dist-info/RECORD
