Metadata-Version: 2.1
Name: tinder.py
Version: 0.1.1
Summary: 
Author: Tiago Vilela
Author-email: tiagovla@gmail.com
Requires-Python: >=3.8,<4.0
Classifier: Programming Language :: Python :: 3
Classifier: Programming Language :: Python :: 3.10
Classifier: Programming Language :: Python :: 3.8
Classifier: Programming Language :: Python :: 3.9
Requires-Dist: aiohttp (>=3.6.2,<4.0.0)
Requires-Dist: pytest (>=7.1.2,<8.0.0)
